stackbased_fsm/__init__.py
stackbased_fsm/py.typed
stackbased_fsm/state_machine.py
stackbased_fsm-0.1.dist-info/LICENSE
stackbased_fsm-0.1.dist-info/WHEEL
stackbased_fsm-0.1.dist-info/METADATA
stackbased_fsm-0.1.dist-info/RECORD
