Metadata-Version: 2.1
Name: stackbased-fsm
Version: 0.1
Summary: Stack-Based Finite State Machine
License: BSD 3-Clause
Author: John Bywater
Author-email: john.bywater@appropriatesoftware.net
Requires-Python: >=3.8,<4.0
Classifier: Development Status :: 3 - Alpha
Classifier: License :: OSI Approved :: BSD License
Classifier: License :: Other/Proprietary License
Classifier: Programming Language :: Python
Classifier: Programming Language :: Python :: 3
Classifier: Programming Language :: Python :: 3.10
Classifier: Programming Language :: Python :: 3.11
Classifier: Programming Language :: Python :: 3.8
Classifier: Programming Language :: Python :: 3.9
